ncPyTools/__init__.py
ncPyTools/ncoGridFile.py
ncPyTools/netCDFReduce.py
ncPyTools/netCDFTemplate.py
ncPyTools/netCDFView.py
ncPyTools-20.4.dist-info/LICENSE.txt
ncPyTools-20.4.dist-info/METADATA
ncPyTools-20.4.dist-info/WHEEL
ncPyTools-20.4.dist-info/entry_points.txt
ncPyTools-20.4.dist-info/top_level.txt
ncPyTools-20.4.dist-info/RECORD
