Metadata-Version: 2.1
Name: ncPyTools
Version: 20.4
Summary: Python processing of netcdf files.
Home-page: https://github.com/mommebutenschoen/ncpytools
Author: Momme Butenschön
Author-email: mommebu@yahoo.de
License: GPL
Keywords: netcdf
Platform: UNKNOWN
Classifier: Development Status :: 4 - Beta
Classifier: Intended Audience :: Science/Research
Classifier: Topic :: Software Development :: Libraries :: Python Modules
Classifier: License :: OSI Approved :: GNU General Public License (GPL)
Classifier: Programming Language :: Python :: 2
Classifier: Programming Language :: Python :: 2.6
Classifier: Programming Language :: Python :: 2.7
Classifier: Programming Language :: Python :: 3
Classifier: Programming Language :: Python :: 3.3
Classifier: Programming Language :: Python :: 3.4
Classifier: Programming Language :: Python :: 3.5
Requires-Dist: netCDF4
Requires-Dist: pyyaml
Requires-Dist: numpy
Provides-Extra: dev
Requires-Dist: check-manifest ; extra == 'dev'
Provides-Extra: test
